PyEyeSim/__init__.py
PyEyeSim/_comparegroups.py
PyEyeSim/_dataproc.py
PyEyeSim/_hmm.py
PyEyeSim/_scanpathsim.py
PyEyeSim/_stats.py
PyEyeSim/_visuals.py
PyEyeSim/hmmhelper.py
PyEyeSim/pyeyesim.py
PyEyeSim/pyeyesim_old.py
PyEyeSim/scanpathshelpdebug.py
PyEyeSim/scanpathsimhelper.py
PyEyeSim/statshelper.py
PyEyeSim/test.py
PyEyeSim/visualhelper.py
pyeyesim-0.4.0.dist-info/METADATA
pyeyesim-0.4.0.dist-info/WHEEL
pyeyesim-0.4.0.dist-info/top_level.txt
pyeyesim-0.4.0.dist-info/RECORD
