Metadata-Version: 2.1
Name: pyeyesim
Version: 0.4.0
Summary: Eye movement analysis and visualization package, with a focus on fixation map and scanpath similarity
Author: jozsef arato
Author-email: Jozsef Arato <jozsef.arato@gmail.com>
Project-URL: Homepage, https://github.com/jozsarato/PyEyeSim
Project-URL: Issues, https://github.com/jozsarato/PyEyeSim/issues
Classifier: Programming Language :: Python :: 3
Requires-Python: >=3.8
Requires-Dist: numpy
Requires-Dist: scipy
Requires-Dist: pandas
Requires-Dist: scikit-image
Requires-Dist: matplotlib
